json_and_merge/__init__.py
json_and_merge/json_merge.py
json_and_merge/modules/__init__.py
json_and_merge-1.0.4.dist-info/LICENSE
json_and_merge-1.0.4.dist-info/METADATA
json_and_merge-1.0.4.dist-info/WHEEL
json_and_merge-1.0.4.dist-info/top_level.txt
json_and_merge-1.0.4.dist-info/RECORD
