Metadata-Version: 2.1
Name: json-and-merge
Version: 1.0.4
Summary: A lightweight solution to validate and merge JSON files, in Python
Home-page: https://github.com/Whoeza/json_and_merge
Author: Whoeza
License: GNU GPLv3
Project-URL: Bug Tracker, https://github.com/Whoeza/json_and_merge/issues
Classifier: Intended Audience :: Developers
Classifier: License :: OSI Approved :: GNU General Public License v3 (GPLv3)
Classifier: Operating System :: OS Independent
Classifier: Programming Language :: Python :: 3
Requires-Python: >=3.10
License-File: LICENSE
Requires-Dist: json-and-validation (>=1.0.0)
Requires-Dist: dict-and-union-with (>=1.0.0)
